popularity_contest/__init__.py
popularity_contest/reporter.py
popularity_contest-0.4.1.dist-info/LICENSE
popularity_contest-0.4.1.dist-info/METADATA
popularity_contest-0.4.1.dist-info/WHEEL
popularity_contest-0.4.1.dist-info/top_level.txt
popularity_contest-0.4.1.dist-info/RECORD
