Metadata-Version: 2.1
Name: popularity-contest
Version: 0.4.1
Summary: Privacy-friendly data collection of the libraries your users are using
Home-page: https://github.com/yuvipanda/python-popularity-contest
Author: Yuvi Panda
License: UNKNOWN
Platform: UNKNOWN
License-File: LICENSE
Requires-Dist: statsd
Requires-Dist: importlib-metadata
